ovos_dialog_normalizer_plugin/__init__.py
ovos_dialog_normalizer_plugin/version.py
ovos_dialog_normalizer_plugin-0.0.1.dist-info/METADATA
ovos_dialog_normalizer_plugin-0.0.1.dist-info/WHEEL
ovos_dialog_normalizer_plugin-0.0.1.dist-info/entry_points.txt
ovos_dialog_normalizer_plugin-0.0.1.dist-info/top_level.txt
ovos_dialog_normalizer_plugin-0.0.1.dist-info/zip-safe
ovos_dialog_normalizer_plugin-0.0.1.dist-info/RECORD
