Metadata-Version: 2.1
Name: ovos-dialog-normalizer-plugin
Version: 0.0.1
Summary: A question solver plugin for ovos
Home-page: https://github.com/OpenVoiceOS/ovos-dialog-normalizer-plugin
Author: jarbasai
Author-email: jarbasai@mailfence.com
License: MIT
Keywords: ovos plugin utterance dialog TTS normalization
Requires-Dist: ovos-plugin-manager
Requires-Dist: ovos-number-parser>=0.3.0
